christis/__init__.py
christis/cmd_config/generate.py
christis/cmd_config/view.py
christis/cmd_database/view.py
christis/cmd_user/role.py
christis/cmd_user/view.py
christis/config.py
christis/database.py
christis/engine/__init__.py
christis/engine/core/__init__.py
christis/engine/core/cn.py
christis/engine/core/email.py
christis/engine/core/general.py
christis/engine/insert/user_table.py
christis/engine/process/__init__.py
christis/engine/process/check.py
christis/engine/process/generate_enteries.py
christis/main.py
christis/role.py
christis/user.py
christis/utils/__init__.py
christis/utils/config_parser.py
christis/utils/general.py
christis/vars.py
christis-0.1.0.dist-info/entry_points.txt
christis-0.1.0.dist-info/WHEEL
christis-0.1.0.dist-info/METADATA
christis-0.1.0.dist-info/RECORD
